fds/__init__.py
fds/sdk/__init__.py
fds/sdk/SPGlobalFixedIncomeEvaluatedPricesandAnalytics/__init__.py
fds/sdk/SPGlobalFixedIncomeEvaluatedPricesandAnalytics/api_client.py
fds/sdk/SPGlobalFixedIncomeEvaluatedPricesandAnalytics/configuration.py
fds/sdk/SPGlobalFixedIncomeEvaluatedPricesandAnalytics/exceptions.py
fds/sdk/SPGlobalFixedIncomeEvaluatedPricesandAnalytics/model_utils.py
fds/sdk/SPGlobalFixedIncomeEvaluatedPricesandAnalytics/rest.py
fds/sdk/SPGlobalFixedIncomeEvaluatedPricesandAnalytics/api/__init__.py
fds/sdk/SPGlobalFixedIncomeEvaluatedPricesandAnalytics/api/abs_details_api.py
fds/sdk/SPGlobalFixedIncomeEvaluatedPricesandAnalytics/api/coupon_api.py
fds/sdk/SPGlobalFixedIncomeEvaluatedPricesandAnalytics/api/issuer_yield_curve_api.py
fds/sdk/SPGlobalFixedIncomeEvaluatedPricesandAnalytics/api/meta_api.py
fds/sdk/SPGlobalFixedIncomeEvaluatedPricesandAnalytics/api/prices_api.py
fds/sdk/SPGlobalFixedIncomeEvaluatedPricesandAnalytics/api/sensitivity_api.py
fds/sdk/SPGlobalFixedIncomeEvaluatedPricesandAnalytics/api/spread_api.py
fds/sdk/SPGlobalFixedIncomeEvaluatedPricesandAnalytics/api/yield_api.py
fds/sdk/SPGlobalFixedIncomeEvaluatedPricesandAnalytics/apis/__init__.py
fds/sdk/SPGlobalFixedIncomeEvaluatedPricesandAnalytics/model/__init__.py
fds/sdk/SPGlobalFixedIncomeEvaluatedPricesandAnalytics/model/abs_details.py
fds/sdk/SPGlobalFixedIncomeEvaluatedPricesandAnalytics/model/abs_details_request.py
fds/sdk/SPGlobalFixedIncomeEvaluatedPricesandAnalytics/model/abs_details_response.py
fds/sdk/SPGlobalFixedIncomeEvaluatedPricesandAnalytics/model/bond_coupon.py
fds/sdk/SPGlobalFixedIncomeEvaluatedPricesandAnalytics/model/bond_coupon_request.py
fds/sdk/SPGlobalFixedIncomeEvaluatedPricesandAnalytics/model/bond_coupon_response.py
fds/sdk/SPGlobalFixedIncomeEvaluatedPricesandAnalytics/model/bond_issuer_yield_curve.py
fds/sdk/SPGlobalFixedIncomeEvaluatedPricesandAnalytics/model/bond_issuer_yield_curve_request.py
fds.sdk.SPGlobalFixedIncomeEvaluatedPricesandAnalytics-0.1.14.dist-info/LICENSE
fds.sdk.SPGlobalFixedIncomeEvaluatedPricesandAnalytics-0.1.14.dist-info/METADATA
fds.sdk.SPGlobalFixedIncomeEvaluatedPricesandAnalytics-0.1.14.dist-info/WHEEL
fds.sdk.SPGlobalFixedIncomeEvaluatedPricesandAnalytics-0.1.14.dist-info/top_level.txt
fds.sdk.SPGlobalFixedIncomeEvaluatedPricesandAnalytics-0.1.14.dist-info/RECORD
